<?xml version="1.0" encoding="UTF-8"?>
<lint>
    
    <!-- Ignore the NewApi issue in the nineoldandroids files -->
    <issue id="NewApi">
        <ignore path="src/com/nineoldandroids/" />
    </issue>
    
    <!-- Ignore the InlinedApi issue in the nineoldandroids files -->
    <issue id="InlinedApi">
        <ignore path="src/com/nineoldandroids/" />
    </issue>
    
    <!-- Ignore the UnusedResources issue in the flags (which used dynamicly) and image which currently not in use but will be in the future -->
    <issue id="UnusedResources">
        <ignore path="res/drawable*/np__flag*.png" />
        <ignore path="res/drawable*/np__ic_auto_complete_text_box_handle.png" />
        <ignore path="res/drawable*/np__ic_buddies_more.png" />
        <ignore path="res/drawable*/np__ic_gamestream_add_profile_picture_player.png" />
        <ignore path="res/drawable*/np__ic_gamestream_new_stories.png" />
        <ignore path="res/drawable*/np__ic_post_upload_image.png" />
        <!-- Will bew used in the future -->
        <ignore path="res/drawable*/np__empty_state_arrow_up.png" />
        <ignore path="res/drawable*/np__empty_state_hands_side.png" />
        <ignore path="res/drawable*/np__empty_state_panic_mouth.png" />
        <ignore path="res/drawable*/np__empty_state_sad_mouth.png" />
        <ignore path="res/drawable*/np__ic_dialog_error.png" />
        <ignore path="res/drawable*/np__tournament_loading_sync_waiting.png" />
        
        <ignore path="res/layout/np__layout_date_picker_header_view.xml" />
    </issue>
    
    <!-- Ignore the ContentDescription issue in the layouts -->
    <issue id="ContentDescription">
        <ignore path="res/layout/" />
    </issue>
    
    <!-- Ignore the Overdraw issue since we use dynamic background -->
    <issue id="Overdraw">
        <ignore path="res/layout/" />
    </issue>
    
    <!-- Ignore the RtlSymmetry -->
    <issue id="RtlSymmetry">
        <ignore path="res/layout/" />
    </issue>
    
    <!-- Ignore the RtlHardcoded -->
    <issue id="RtlHardcoded">
        <ignore path="res/layout/" />
    </issue>
    
    <issue id="IconColors">
        <ignore path="res/" />
    </issue>
    
    <!-- Ignore the IconDuplicatesConfig issue in the known duplicated icons -->
    <issue id="IconDuplicatesConfig">
        <ignore path="res/drawable*/np__crop_divider.9.png" />	<!-- Crop package doesn't have xxhdpi icons -->
        <ignore path="res/drawable*/np__crop_ic_cancel.png" />	<!-- Crop package doesn't have xxhdpi icons -->
        <ignore path="res/drawable*/np__crop_ic_done.png" />	<!-- Crop package doesn't have xxhdpi icons -->
        <ignore path="res/drawable*/np__crop_tile.png" />		<!-- Crop package doesn't have xxhdpi icons -->
    </issue>
    
    <!-- Ignore the IconDuplicatesConfig issue crop package - external open source code -->
    <issue id="IconDipSize">
        <ignore path="res/drawable*/np__crop_ic_cancel.png" />
        <ignore path="res/drawable*/np__crop_ic_done.png" />	
        <ignore path="res/drawable*/np__crop_tile.png" />		
    </issue>
    
    <!-- Ignore the UselessParent issue since we use dynamic background and we need two layers - for the background image and the transparent layer-->
    <issue id="UselessParent">
        <ignore path="res/layout/" />
    </issue>
    
    <!-- Ignore the IconDuplicatesConfig fro crop resources since this library doesn't have icon for all sizes so we duplicated those we needed-->
	<issue id="IconDuplicatesConfig">
        <ignore path="res/drawable*/crop*" />
    </issue>
    
    <!-- Ignore the IconDuplicatesConfig fro crop resources since this library doesn't have icon for all sizes so we duplicated those we needed-->
	<issue id="IconDipSize">
        <ignore path="res/drawable*/crop*" />
    </issue>
    
    <!-- Ignore the Assert issue in the okhttp files -->
    <issue id="Assert">
        <ignore path="src/com/squareup/okhttp/" />
        <ignore path="src/com/google/" />
        <ignore path="src/com/nineoldandroids/" />
    </issue>
    
    <!-- Ignore the UseSparseArrays issue in the okhttp files -->
    <issue id="UseSparseArrays">
        <ignore path="src/com/squareup/okhttp/" />
    </issue>
    
    <!-- Ignore the MergeRootFrame issue -->
    <issue id="MergeRootFrame">
        <ignore path="res/layout/np__activity_main.xml" />
    </issue>
    
    <!-- Ignore the Assert issue in the okhttp files -->
    <issue id="DefaultLocale">
        <ignore path="src/com/squareup/okhttp/" />
        <ignore path="src/com/google/" />
        <ignore path="src/com/nineoldandroids/" />
    </issue>
    
        <!-- Ignore the UselessParent issue since we use dynamic background and we need two layers - for the background image and the transparent layer-->
    <issue id="UselessParent">
        <ignore path="res/drawable*/crop*" />
    </issue>
    
</lint>